README.rst
setup.py
scrapy_kafka/__init__.py
scrapy_kafka/pipelines.py
scrapy_kafka/spiders.py
scrapy_kafka.egg-info/PKG-INFO
scrapy_kafka.egg-info/SOURCES.txt
scrapy_kafka.egg-info/dependency_links.txt
scrapy_kafka.egg-info/requires.txt
scrapy_kafka.egg-info/top_level.txt