Metadata-Version: 1.1
Name: scrapy-kafka
Version: 0.1.1
Summary: Kafka-based components for Scrapy
Home-page: https://github.com/dfdeshom/scrapy-kafka
Author: Didier Deshommes
Author-email: dfdeshom@gmail.com
License: BSD
Platform: UNKNOWN
Classifier: Programming Language :: Python
Classifier: Development Status :: 4 - Beta
Classifier: Intended Audience :: Developers
